cdcam/__init__.py
cdcam/interventions.py
cdcam/model.py
cdcam-1.0.1.dist-info/LICENSE
cdcam-1.0.1.dist-info/METADATA
cdcam-1.0.1.dist-info/WHEEL
cdcam-1.0.1.dist-info/entry_points.txt
cdcam-1.0.1.dist-info/top_level.txt
cdcam-1.0.1.dist-info/RECORD
