Metadata-Version: 2.1
Name: cdcam
Version: 1.0.1
Summary: Cambridge Digital Communications Assessment Model
Home-page: https://github.com/nismod/cdcam
Author: Edward J. Oughton
Author-email: edward.oughton@ouce.ox.ac.uk
License: MIT License
Platform: UNKNOWN
Classifier: Development Status :: 5 - Production/Stable
Classifier: Intended Audience :: Science/Research
Classifier: License :: OSI Approved :: MIT License
Classifier: Programming Language :: Python
Classifier: Programming Language :: Python :: 3
Classifier: Topic :: Scientific/Engineering
Classifier: Topic :: Communications :: Telephony
